quri_parts/openfermion/NOTICE
quri_parts/openfermion/__init__.py
quri_parts/openfermion/ansatz/__init__.py
quri_parts/openfermion/ansatz/kupccgsd.py
quri_parts/openfermion/ansatz/uccsd.py
quri_parts/openfermion/mol/__init__.py
quri_parts/openfermion/mol/hamiltonian.py
quri_parts/openfermion/operator/__init__.py
quri_parts/openfermion/operator/conversions.py
quri_parts/openfermion/operator/fermion_operator.py
quri_parts/openfermion/py.typed
quri_parts/openfermion/transforms/__init__.py
quri_parts/openfermion/utils/__init__.py
quri_parts/openfermion/utils/add_exp_excitation_gates_trotter_decomposition.py
quri_parts/openfermion/utils/post_selection_filters.py
quri_parts_openfermion-17.0.0.dist-info/LICENSE
quri_parts_openfermion-17.0.0.dist-info/METADATA
quri_parts_openfermion-17.0.0.dist-info/WHEEL
quri_parts_openfermion-17.0.0.dist-info/RECORD
